

{
  "openapi": "3.0.0",
  "info": {
    "description": "API para acceder a datos del Instituto Nacional de Estadísticas",
    "version": "1.0.0",
    "title": "Importine",
    "contact": {
      "email": "kilehmannm@ine.gob.cl"
    },
    "license": {
      "name": "MIT",
      "url": "https://opensource.org/licenses/MIT"
    }
  },
  "servers": [
    {
      "url": "/"
    }
  ],
  "tags": [
    {
      "name": "Book Request",
      "description": "Example API for requesting and return book requests"
    }
  ],
  "paths": {
    "/datasets": {
      "get": {
        "tags": [
          "Book Request"
        ],
        "summary": "Retorna listado de datasets disponibles",
        "responses": {
          "200": {
            "description": "OK",
            "schema": {
              "$ref": "#/components/schemas/bookRequests"
            }
          }
        }
      },

    },
    "/data": {
      "parameters": [
        {
          "name": "id",
          "in": "path",
          "required": true,
          "description": "ID of the cat that we want to match",
          "type": "string"
        },
        {
          "name": "year",
          "required": true,
          "description": "año de publicación de la encuesta",
          "type": "string"
         } 
      ],
      "get": {
        "tags": [
          "Book Request"
        ],
        "summary": "Get book request with given ID",
        "parameters": [
          {
            "in": "path",
            "name": "id",
            "required": true,
            "description": "Book Request id",
            "schema": {
              "$ref": "#/components/schemas/id"
            }
          }
        ],
        "responses": {
          "200": {
            "description": "OK",
            "schema": {
              "$ref": "#/components/schemas/bookRequest"
            }
          },
          "400": {
            "description": "Failed. Misunderstood Request."
          },
          "404": {
            "description": "Failed. Book request not found."
          }
        }
      },
    }
  },
  "components": {
    "schemas": {
      "id": {
        "properties": {
          "uuid": {
            "type": "string"
          }
        }
      },
      "bookRequestPostBody": {
        "type": "object",
        "properties": {
          "title": {
            "type": "string",
            "format": "string"
          },
          "email": {
            "type": "string",
            "format": "email"
          }
        }
      },
      "bookRequest": {
        "type": "object",
        "properties": {
          "title": {
            "type": "string",
            "format": "string"
          },
          "email": {
            "type": "string",
            "format": "email"
          },
          "timestamp": {
            "type": "string",
            "format": "number"
          }
        }
      },
      "bookRequests": {
        "type": "object",
        "properties": {
          "bookRequest": {
            "type": "object",
            "additionalProperties": {
              "$ref": "#/components/schemas/bookRequest"
            }
          }
        }
      }
    }
  }
}
